psr_formats/__init__.py
psr_formats/dada_file.py
psr_formats/data_file.py
psr_formats/util.py
psr_formats-0.2.2.dist-info/WHEEL
psr_formats-0.2.2.dist-info/METADATA
psr_formats-0.2.2.dist-info/RECORD
