Metadata-Version: 2.1
Name: psr-formats
Version: 0.2.2
Summary: Various formats used in pulsar signal processing
License: MIT
Author: Dean Shaff
Author-email: dshaff@swin.edu.au
Requires-Python: >=3.6,<4.0
Classifier: License :: OSI Approved :: MIT License
Classifier: Programming Language :: Python :: 3
Classifier: Programming Language :: Python :: 3.6
Classifier: Programming Language :: Python :: 3.7
Requires-Dist: astropy (>=3.2,<4.0)
Requires-Dist: numpy (>=1.16,<2.0)
